vrp_cli-1.24.0.dist-info/METADATA
vrp_cli-1.24.0.dist-info/WHEEL
vrp_cli/__init__.py
vrp_cli/vrp_cli.cpython-39-darwin.so
vrp_cli-1.24.0.dist-info/RECORD
