Metadata-Version: 2.1
Name: vrp-cli
Version: 1.24.0
Summary: A command line interface for VRP solver
Keywords: vrp,optimization
Home-Page: https://github.com/reinterpretcat/vrp
Author: Ilya Builuk <ilya.builuk@gmail.com>
Author-email: Ilya Builuk <ilya.builuk@gmail.com>
License: Apache-2.0
Project-URL: Source Code, https://github.com/reinterpretcat/vrp
